HeliosEthernetSilaaCooling/Helios_Errors.py
HeliosEthernetSilaaCooling/Helios_Ethernet.py
HeliosEthernetSilaaCooling/Helios_HexConverter.py
HeliosEthernetSilaaCooling/__init__.py
HeliosEthernetSilaaCooling-1.2.3.dist-info/LICENSE
HeliosEthernetSilaaCooling-1.2.3.dist-info/METADATA
HeliosEthernetSilaaCooling-1.2.3.dist-info/WHEEL
HeliosEthernetSilaaCooling-1.2.3.dist-info/top_level.txt
HeliosEthernetSilaaCooling-1.2.3.dist-info/RECORD
