Metadata-Version: 2.1
Name: HeliosEthernetSilaaCooling
Version: 1.2.3
Summary: This package is designed to control a Helios KWL EC 170 W via Modbus TCP/IP
Home-page: https://gogs.es-lab.de/SilaaCooling/Simulationsmodell_SilaaCooling/src/master/Helios%20Modbus
Author: ['Alexander Teubert', 'Stefanie Fiedler']
License: UNKNOWN
Platform: UNKNOWN
Classifier: Programming Language :: Python :: 3
Classifier: Operating System :: OS Independent
Classifier: License :: OSI Approved :: GNU General Public License v3 (GPLv3)
Classifier: Natural Language :: English
Requires-Python: >=3.5.2
Requires-Dist: EasyModbusSilaaCooling
Requires-Dist: pyserial
